{
  "elevations": {
    "stroked": {
      "depth+4": {
        "value": [
          {
            "color": "{color.background.accent.gray.bolder}14",
            "type": "dropShadow",
            "x": "0",
            "y": "16",
            "blur": "26",
            "spread": "-6"
          },
          {
            "color": "{color.background.accent.gray.bolder}0a",
            "type": "dropShadow",
            "x": "0",
            "y": "0",
            "blur": "3",
            "spread": "-1"
          },
          {
            "color": "{color.background.accent.gray.bolder}14",
            "type": "dropShadow",
            "x": "0",
            "y": "0",
            "blur": "0",
            "spread": "1"
          }
        ],
        "type": "boxShadow"
      },
      "depth+3": {
        "value": [
          {
            "color": "{color.background.accent.gray.bolder}14",
            "type": "dropShadow",
            "x": "0",
            "y": "8",
            "blur": "16",
            "spread": "0"
          },
          {
            "color": "{color.background.accent.gray.bolder}14",
            "type": "dropShadow",
            "x": "0",
            "y": "0",
            "blur": "0",
            "spread": "1"
          }
        ],
        "type": "boxShadow"
      },
      "depth+2": {
        "value": [
          {
            "color": "{color.background.accent.gray.bolder}1a",
            "type": "dropShadow",
            "x": "0",
            "y": "2",
            "blur": "12",
            "spread": "-1"
          },
          {
            "color": "{color.background.accent.gray.bolder}0a",
            "type": "dropShadow",
            "x": "0",
            "y": "2",
            "blur": "2",
            "spread": "-1"
          },
          {
            "color": "{color.background.accent.gray.bolder}14",
            "type": "dropShadow",
            "x": "0",
            "y": "0",
            "blur": "0",
            "spread": "1"
          }
        ],
        "type": "boxShadow"
      },
      "depth+1": {
        "value": [
          {
            "color": "{blue.blue900}14",
            "type": "dropShadow",
            "x": "0",
            "y": "2",
            "blur": "3",
            "spread": "-2"
          },
          {
            "color": "{blue.blue900}14",
            "type": "dropShadow",
            "x": "0",
            "y": "2",
            "blur": "2",
            "spread": "0"
          },
          {
            "color": "{color.border.default}",
            "type": "dropShadow",
            "x": "0",
            "y": "0",
            "blur": "0",
            "spread": "1"
          }
        ],
        "type": "boxShadow"
      },
      "highlight-border": {
        "value": [
          {
            "color": "{color.border.default}",
            "type": "dropShadow",
            "x": "0",
            "y": "0",
            "blur": "0",
            "spread": "1"
          }
        ],
        "type": "boxShadow"
      }
    },
    "unstroked": {
      "depth+4": {
        "value": [
          {
            "color": "{elevation.shadow.overflow.perimeter}",
            "type": "dropShadow",
            "x": "0",
            "y": "16",
            "blur": "26",
            "spread": "-6"
          },
          {
            "color": "{elevation.shadow.overflow.spread}",
            "type": "dropShadow",
            "x": "0",
            "y": "0",
            "blur": "3",
            "spread": "-1"
          }
        ],
        "type": "boxShadow"
      },
      "depth+3": {
        "value": {
          "x": "0",
          "y": "8",
          "blur": "16",
          "spread": "0",
          "color": "{color.background.accent.gray.bolder}1f",
          "type": "dropShadow"
        },
        "type": "boxShadow"
      },
      "depth+2": {
        "value": [
          {
            "color": "{color.background.accent.gray.bolder}1a",
            "type": "dropShadow",
            "x": "0",
            "y": "2",
            "blur": "12",
            "spread": "-1"
          },
          {
            "color": "{color.background.accent.gray.bolder}14",
            "type": "dropShadow",
            "x": "0",
            "y": "2",
            "blur": "2",
            "spread": "-1"
          }
        ],
        "type": "boxShadow"
      },
      "depth+1": {
        "value": {
          "x": "0",
          "y": "1",
          "blur": "1",
          "spread": "0",
          "color": "{color.background.accent.gray.bolder}4f",
          "type": "dropShadow"
        },
        "type": "boxShadow"
      }
    }
  },
  "focus": {
    "default Focus + 1px White Offset": {
      "value": [
        {
          "color": "{color.background.accent.gray.subtlest}",
          "type": "dropShadow",
          "x": "0",
          "y": "0",
          "blur": "0",
          "spread": "1"
        },
        {
          "color": "{color.border.focused}",
          "type": "dropShadow",
          "x": "0",
          "y": "0",
          "blur": "0",
          "spread": "3"
        }
      ],
      "type": "boxShadow"
    },
    "default Focus": {
      "value": {
        "x": "0",
        "y": "0",
        "blur": "0",
        "spread": "2",
        "color": "{color.border.focused}",
        "type": "dropShadow"
      },
      "type": "boxShadow"
    }
  },
  "effect": {
    "white Offset": {
      "value": {
        "x": "0",
        "y": "0",
        "blur": "0",
        "spread": "2",
        "color": "{neutral.neutral0}",
        "type": "dropShadow"
      },
      "type": "boxShadow"
    },
    "inner default Border": {
      "value": {
        "x": "0",
        "y": "0",
        "blur": "0",
        "spread": "1",
        "color": "{color.border.default}",
        "type": "innerShadow"
      },
      "type": "boxShadow"
    }
  }
}